[{"show_id":"s1","type":"Movie","title":"Dick Johnson Is Dead","director":"Kirsten Johnson","country":"United States","date_added":"9/25/2021","release_year":"2020","rating":"PG-13","duration":"90 min","listed_in":"Documentaries"},{"show_id":"s3","type":"TV Show","title":"Ganglands","director":"Julien Leclercq","country":"France","date_added":"9/24/2021","release_year":"2021","rating":"TV-MA","duration":"1 Season","listed_in":"Crime TV Shows, International TV Shows, TV Action & Adventure"},{"show_id":"s6","type":"TV Show","title":"Midnight Mass","director":"Mike Flanagan","country":"United States","date_added":"9/24/2021","release_year":"2021","rating":"TV-MA","duration":"1 Season","listed_in":"TV Dramas, TV Horror, TV Mysteries"},{"show_id":"s14","type":"Movie","title":"Confessions of an Invisible Girl","director":"Bruno Garotti","country":"Brazil","date_added":"9/22/2021","release_year":"2021","rating":"TV-PG","duration":"91 min","listed_in":"Children & Family Movies, Comedies"},{"show_id":"s8","type":"Movie","title":"Sankofa","director":"Haile Gerima","country":"United States","date_added":"9/24/2021","release_year":"1993","rating":"TV-MA","duration":"125 min","listed_in":"Dramas, Independent Movies, International Movies"},{"show_id":"s9","type":"TV Show","title":"The Great British Baking Show","director":"Andy Devonshire","country":"United Kingdom","date_added":"9/24/2021","release_year":"2021","rating":"TV-14","duration":"9 Seasons","listed_in":"British TV Shows, Reality TV"},{"show_id":"s10","type":"Movie","title":"The Starling","director":"Theodore Melfi","country":"United States","date_added":"9/24/2021","release_year":"2021","rating":"PG-13","duration":"104 min","listed_in":"Comedies, Dramas"},{"show_id":"s939","type":"Movie","title":"Motu Patlu in the Game of Zones","director":"Suhas Kadav","country":"India","date_added":"5/1/2021","release_year":"2019","rating":"TV-Y7","duration":"87 min","listed_in":"Children & Family Movies, Comedies, Music & Musicals"},{"show_id":"s13","type":"Movie","title":"Je Suis Karl","director":"Christian Schwochow","country":"Germany","date_added":"9/23/2021","release_year":"2021","rating":"TV-MA","duration":"127 min","listed_in":"Dramas, International Movies"},{"show_id":"s940","type":"Movie","title":"Motu Patlu in Wonderland","director":"Suhas Kadav","country":"India","date_added":"5/1/2021","release_year":"2013","rating":"TV-Y7","duration":"76 min","listed_in":"Children & Family Movies, Music & Musicals"},{"show_id":"s941","type":"Movie","title":"Motu Patlu: Deep Sea Adventure","director":"Suhas Kadav","country":"India","date_added":"5/1/2021","release_year":"2014","rating":"TV-Y7","duration":"76 min","listed_in":"Children & Family Movies, Comedies"},{"show_id":"s942","type":"Movie","title":"Motu Patlu: Mission Moon","director":"Suhas Kadav","country":"India","date_added":"5/1/2021","release_year":"2013","rating":"TV-Y7","duration":"71 min","listed_in":"Children & Family Movies, Comedies"},{"show_id":"s852","type":"Movie","title":"99 Songs (Tamil)","director":"Not Given","country":"Pakistan","date_added":"5/21/2021","release_year":"2021","rating":"TV-14","duration":"131 min","listed_in":"Dramas, International Movies, Music & Musicals"},{"show_id":"s471","type":"Movie","title":"Bridgerton - The Afterparty","director":"Krysia Plonka, Kristian Mercado","country":"United States","date_added":"7/13/2021","release_year":"2021","rating":"TV-14","duration":"39 min","listed_in":"Movies"},{"show_id":"s730","type":"Movie","title":"Bling Empire - The Afterparty","director":"Krysia Plonka, Kristian Mercado","country":"United States","date_added":"6/12/2021","release_year":"2021","rating":"TV-MA","duration":"36 min","listed_in":"Movies"},{"show_id":"s731","type":"Movie","title":"Cobra Kai - The Afterparty","director":"Krysia Plonka, Kristian Mercado","country":"United States","date_added":"6/12/2021","release_year":"2021","rating":"TV-MA","duration":"34 min","listed_in":"Movies"},{"show_id":"s913","type":"Movie","title":"The Circle - The Afterparty","director":"Krysia Plonka, Kristian Mercado","country":"United States","date_added":"5/7/2021","release_year":"2021","rating":"TV-14","duration":"35 min","listed_in":"Comedies"},{"show_id":"s4","type":"TV Show","title":"Jailbirds New Orleans","director":"Not Given","country":"Pakistan","date_added":"9/24/2021","release_year":"2021","rating":"TV-MA","duration":"1 Season","listed_in":"Docuseries, Reality TV"},{"show_id":"s15","type":"TV Show","title":"Crime Stories: India Detectives","director":"Not Given","country":"Pakistan","date_added":"9/22/2021","release_year":"2021","rating":"TV-MA","duration":"1 Season","listed_in":"British TV Shows, Crime TV Shows, Docuseries"},{"show_id":"s3232","type":"Movie","title":"True: Winter Wishes","director":"Mark Thornton, Todd Kauffman","country":"United States","date_added":"11/26/2019","release_year":"2019","rating":"TV-Y","duration":"46 min","listed_in":"Children & Family Movies"},{"show_id":"s4832","type":"TV Show","title":"True: Magical Friends","director":"Mark Thornton, Todd Kauffman","country":"United States","date_added":"6/15/2018","release_year":"2018","rating":"TV-Y","duration":"1 Season","listed_in":"Kids' TV"},{"show_id":"s4833","type":"TV Show","title":"True: Wonderful Wishes","director":"Mark Thornton, Todd Kauffman","country":"United States","date_added":"6/15/2018","release_year":"2018","rating":"TV-Y","duration":"1 Season","listed_in":"Kids' TV"},{"show_id":"s4857","type":"TV Show","title":"Dance & Sing with True","director":"Mark Thornton, Todd Kauffman","country":"United States","date_added":"5/18/2018","release_year":"2018","rating":"TV-Y","duration":"1 Season","listed_in":"Kids' TV"},{"show_id":"s7","type":"Movie","title":"My Little Pony: A New Generation","director":"Robert Cullen, José Luis Ucha","country":"Not Given","date_added":"9/24/2021","release_year":"2021","rating":"PG","duration":"91 min","listed_in":"Children & Family Movies"},{"show_id":"s12","type":"TV Show","title":"Bangkok Breaking","director":"Kongkiat Komesiri","country":"Not Given","date_added":"9/23/2021","release_year":"2021","rating":"TV-MA","duration":"1 Season","listed_in":"Crime TV Shows, International TV Shows, TV Action & Adventure"},{"show_id":"s17","type":"Movie","title":"Europe's Most Dangerous Man: Otto Skorzeny in Spain","director":"Pedro de Echave García, Pablo Azorín Williams","country":"Not Given","date_added":"9/22/2021","release_year":"2020","rating":"TV-MA","duration":"67 min","listed_in":"Documentaries, International Movies"},{"show_id":"s7930","type":"Movie","title":"Samudri Lootere","director":"Anirban Majumder","country":"Not Given","date_added":"6/18/2019","release_year":"2018","rating":"TV-Y","duration":"65 min","listed_in":"Children & Family Movies"},{"show_id":"s21","type":"TV Show","title":"Monsters Inside: The 24 Faces of Billy Milligan","director":"Olivier Megaton","country":"United States","date_added":"9/22/2021","release_year":"2021","rating":"TV-14","duration":"1 Season","listed_in":"Crime TV Shows, Docuseries, International TV Shows"},{"show_id":"s24","type":"Movie","title":"Go! Go! Cory Carson: Chrissy Takes the Wheel","director":"Alex Woo, Stanley Moore","country":"United States","date_added":"9/21/2021","release_year":"2021","rating":"TV-Y","duration":"61 min","listed_in":"Children & Family Movies"},{"show_id":"s25","type":"Movie","title":"Jeans","director":"S. Shankar","country":"India","date_added":"9/21/2021","release_year":"1998","rating":"TV-14","duration":"166 min","listed_in":"Comedies, International Movies, Romantic Movies"},{"show_id":"s28","type":"Movie","title":"Grown Ups","director":"Dennis Dugan","country":"United States","date_added":"9/20/2021","release_year":"2010","rating":"PG-13","duration":"103 min","listed_in":"Comedies"},{"show_id":"s29","type":"Movie","title":"Dark Skies","director":"Scott Stewart","country":"United States","date_added":"9/19/2021","release_year":"2013","rating":"PG-13","duration":"97 min","listed_in":"Horror Movies, Sci-Fi & Fantasy"},{"show_id":"s30","type":"Movie","title":"Paranoia","director":"Robert Luketic","country":"United States","date_added":"9/19/2021","release_year":"2013","rating":"PG-13","duration":"106 min","listed_in":"Thrillers"},{"show_id":"s20","type":"TV Show","title":"Jaguar","director":"Not Given","country":"Pakistan","date_added":"9/22/2021","release_year":"2021","rating":"TV-MA","duration":"1 Season","listed_in":"International TV Shows, Spanish-Language TV Shows, TV Action & Adventure"},{"show_id":"s32","type":"TV Show","title":"Chicago Party Aunt","director":"Not Given","country":"Pakistan","date_added":"9/17/2021","release_year":"2021","rating":"TV-MA","duration":"1 Season","listed_in":"TV Comedies"},{"show_id":"s34","type":"TV Show","title":"Squid Game","director":"Not Given","country":"Pakistan","date_added":"9/17/2021","release_year":"2021","rating":"TV-MA","duration":"1 Season","listed_in":"International TV Shows, TV Dramas, TV Thrillers"},{"show_id":"s35","type":"TV Show","title":"Tayo and Little Wizards","director":"Not Given","country":"Pakistan","date_added":"9/17/2021","release_year":"2020","rating":"TV-Y7","duration":"1 Season","listed_in":"Kids' TV"},{"show_id":"s75","type":"TV Show","title":"The World's Most Amazing Vacation Rentals","director":"Not Given","country":"Pakistan","date_added":"9/14/2021","release_year":"2021","rating":"TV-PG","duration":"2 Seasons","listed_in":"Reality TV"},{"show_id":"s84","type":"TV Show","title":"Metal Shop Masters","director":"Not Given","country":"Pakistan","date_added":"9/10/2021","release_year":"2021","rating":"TV-MA","duration":"1 Season","listed_in":"Reality TV"},{"show_id":"s86","type":"TV Show","title":"Pokémon Master Journeys: The Series","director":"Not Given","country":"Pakistan","date_added":"9/10/2021","release_year":"2021","rating":"TV-Y7","duration":"1 Season","listed_in":"Anime Series, Kids' TV"},{"show_id":"s88","type":"TV Show","title":"Titipo Titipo","director":"Not Given","country":"Pakistan","date_added":"9/10/2021","release_year":"2019","rating":"TV-Y","duration":"2 Seasons","listed_in":"Kids' TV, Korean TV Shows"},{"show_id":"s90","type":"TV Show","title":"Mighty Raju","director":"Not Given","country":"Pakistan","date_added":"9/9/2021","release_year":"2017","rating":"TV-Y7","duration":"4 Seasons","listed_in":"Kids' TV"},{"show_id":"s101","type":"TV Show","title":"Tobot Galaxy Detectives","director":"Not Given","country":"Pakistan","date_added":"9/7/2021","release_year":"2019","rating":"TV-Y7","duration":"2 Seasons","listed_in":"Kids' TV"},{"show_id":"s122","type":"TV Show","title":"Hotel Del Luna","director":"Not Given","country":"Pakistan","date_added":"9/2/2021","release_year":"2019","rating":"TV-14","duration":"1 Season","listed_in":"International TV Shows, Romantic TV Shows, TV Comedies"},{"show_id":"s133","type":"TV Show","title":"Brave Animated Series","director":"Not Given","country":"Pakistan","date_added":"9/1/2021","release_year":"2021","rating":"TV-MA","duration":"1 Season","listed_in":"International TV Shows, TV Action & Adventure, TV Comedies"},{"show_id":"s148","type":"TV Show","title":"How to Be a Cowboy","director":"Not Given","country":"Pakistan","date_added":"9/1/2021","release_year":"2021","rating":"TV-PG","duration":"1 Season","listed_in":"Reality TV"},{"show_id":"s166","type":"TV Show","title":"Oldsters","director":"Not Given","country":"Pakistan","date_added":"9/1/2021","release_year":"2019","rating":"TV-MA","duration":"1 Season","listed_in":"Crime TV Shows, International TV Shows, Spanish-Language TV Shows"},{"show_id":"s190","type":"TV Show","title":"Bread Barbershop","director":"Not Given","country":"Pakistan","date_added":"8/28/2021","release_year":"2020","rating":"TV-Y","duration":"2 Seasons","listed_in":"Kids' TV, TV Comedies"},{"show_id":"s182","type":"TV Show","title":"Turning Point: 9/11 and the War on Terror","director":"Not Given","country":"Pakistan","date_added":"9/1/2021","release_year":"2021","rating":"TV-14","duration":"1 Season","listed_in":"Docuseries"},{"show_id":"s187","type":"TV Show","title":"Hometown Cha-Cha-Cha","director":"Not Given","country":"Pakistan","date_added":"8/29/2021","release_year":"2021","rating":"TV-14","duration":"1 Season","listed_in":"International TV Shows, Romantic TV Shows, TV Comedies"}]
